{
  "courses": [
    { "id": 1, "name": "B.Tech", "fullForm": "Bachelor of Technology" },
    { "id": 2, "name": "B.E", "fullForm": "Bachelor of Engineering" },
    { "id": 3, "name": "BCA", "fullForm": "Bachelor of Computer Applications" },
    { "id": 4, "name": "B.Sc", "fullForm": "Bachelor of Science" },
    { "id": 5, "name": "B.Com", "fullForm": "Bachelor of Commerce" },
    { "id": 6, "name": "BBA", "fullForm": "Bachelor of Business Administration" },
    { "id": 7, "name": "B.Arch", "fullForm": "Bachelor of Architecture" },
    { "id": 8, "name": "BA", "fullForm": "Bachelor of Arts" },
    { "id": 9, "name": "B.Pharm", "fullForm": "Bachelor of Pharmacy" },
    { "id": 10, "name": "B.Ed", "fullForm": "Bachelor of Education" },

    { "id": 11, "name": "M.Tech", "fullForm": "Master of Technology" },
    { "id": 12, "name": "MCA", "fullForm": "Master of Computer Applications" },
    { "id": 13, "name": "M.Sc", "fullForm": "Master of Science" },
    { "id": 14, "name": "MBA", "fullForm": "Master of Business Administration" },
    { "id": 15, "name": "M.Com", "fullForm": "Master of Commerce" },
    { "id": 16, "name": "MA", "fullForm": "Master of Arts" },

    { "id": 17, "name": "B.Tech CSE", "fullForm": "B.Tech in Computer Science and Engineering" },
    { "id": 18, "name": "B.Tech IT", "fullForm": "B.Tech in Information Technology" },
    { "id": 19, "name": "B.Tech AI & ML", "fullForm": "B.Tech in Artificial Intelligence and Machine Learning" },
    { "id": 20, "name": "B.Tech Data Science", "fullForm": "B.Tech in Data Science" },
    { "id": 21, "name": "B.Tech Cyber Security", "fullForm": "B.Tech in Cyber Security" },
    { "id": 22, "name": "B.Tech IoT", "fullForm": "B.Tech in Internet of Things" },
    { "id": 23, "name": "B.Tech Robotics", "fullForm": "B.Tech in Robotics and Automation" },
    { "id": 24, "name": "B.Tech Electronics", "fullForm": "B.Tech in Electronics and Communication Engineering" },
    { "id": 25, "name": "B.Tech Mechanical", "fullForm": "B.Tech in Mechanical Engineering" },
    { "id": 26, "name": "B.Tech Civil", "fullForm": "B.Tech in Civil Engineering" },
    { "id": 27, "name": "B.Tech Aerospace", "fullForm": "B.Tech in Aerospace Engineering" },
    { "id": 28, "name": "B.Tech Biotechnology", "fullForm": "B.Tech in Biotechnology" },
    { "id": 29, "name": "B.Tech Chemical", "fullForm": "B.Tech in Chemical Engineering" },

    { "id": 30, "name": "M.Tech CSE", "fullForm": "M.Tech in Computer Science and Engineering" },
    { "id": 31, "name": "M.Tech Cyber Security", "fullForm": "M.Tech in Cyber Security" },
    { "id": 32, "name": "M.Tech Data Science", "fullForm": "M.Tech in Data Science" },
    { "id": 33, "name": "M.Tech Artificial Intelligence", "fullForm": "M.Tech in Artificial Intelligence" },
    { "id": 34, "name": "M.Tech Machine Learning", "fullForm": "M.Tech in Machine Learning" },
    { "id": 35, "name": "M.Tech IoT", "fullForm": "M.Tech in Internet of Things" },
    { "id": 36, "name": "M.Tech VLSI", "fullForm": "M.Tech in VLSI Design" },
    { "id": 37, "name": "M.Tech Embedded Systems", "fullForm": "M.Tech in Embedded Systems" },

    { "id": 38, "name": "PGDCA", "fullForm": "Post Graduate Diploma in Computer Applications" },
    { "id": 39, "name": "Diploma in Computer Science", "fullForm": "Diploma in Computer Science Engineering" },
    { "id": 40, "name": "Diploma in IT", "fullForm": "Diploma in Information Technology" },
    { "id": 41, "name": "Diploma in AI", "fullForm": "Diploma in Artificial Intelligence" },
    { "id": 42, "name": "Diploma in Data Analytics", "fullForm": "Diploma in Data Analytics" }
  ]
}
